{
  "type": "forge:conditional",
  "recipes": [
    {
      "conditions": [
        {
          "modid": "refinedstorage",
          "type": "forge:mod_loaded"
        }
      ],
      "recipe": {
        "type": "minecraft:crafting_shaped",
        "pattern": [
          "dud",
          "gcg",
          "ded"
        ],
        "key": {
          "d": {
            "tag": "forge:gems/diamond"
          },
          "e": {
            "tag": "forge:gems/emerald"
          },
          "g": {
            "item": "jetboots:obsidian_infused_gold"
          },
          "c": {
            "item": "jetboots:armor_core"
          },
          "u": {
            "item": "refinedstorage:range_upgrade"
          }
        },
        "result": {
          "item": "jetboots:wireless_range_upgrade_rs"
        }
      }
    }
  ]
}